bookings/__init__.py
bookings/admin.py
bookings/apps.py
bookings/models.py
bookings/selectors.py
bookings/services.py
bookings/migrations/0001_initial.py
bookings/migrations/__init__.py
mroudai_django_bookings-0.1.0.dist-info/licenses/LICENSE
mroudai_django_bookings-0.1.0.dist-info/METADATA
mroudai_django_bookings-0.1.0.dist-info/WHEEL
mroudai_django_bookings-0.1.0.dist-info/top_level.txt
mroudai_django_bookings-0.1.0.dist-info/RECORD
