Metadata-Version: 2.4
Name: mroudai-django-bookings
Version: 0.1.0
Summary: Reusable Django app that stores and manages appointment bookings.
Author-email: Kevin Oudai <kevin@mroudai.com>
License: MIT License
Project-URL: Homepage, https://github.com/Kevin-Oudai/django-bookings
Project-URL: Repository, https://github.com/Kevin-Oudai/django-bookings.git
Keywords: django,bookings,appointments
Classifier: Development Status :: 3 - Alpha
Classifier: Framework :: Django
Classifier: Framework :: Django :: 4.2
Classifier: Framework :: Django :: 5.0
Classifier: License :: OSI Approved :: MIT License
Classifier: Operating System :: OS Independent
Classifier: Programming Language :: Python
Classifier: Programming Language :: Python :: 3
Classifier: Programming Language :: Python :: 3 :: Only
Classifier: Programming Language :: Python :: 3.10
Classifier: Programming Language :: Python :: 3.11
Classifier: Programming Language :: Python :: 3.12
Classifier: Topic :: Office/Business
Classifier: Topic :: Software Development :: Libraries :: Python Modules
Requires-Python: >=3.10
License-File: LICENSE
Requires-Dist: Django>=4.2
Dynamic: license-file
